{
  "update_date": "2026-03-27",
  "best_combinations": [
    0,
    16
  ],
  "strategies": [
    {
      "strategy_name": "ATR选股策略",
      "signal_name": "开盘价信号",
      "target_name": "收益率目标 2% / 1天",
      "performance": {
        "success_rate": 0.51666665,
        "stop_loss_rate": 0.125,
        "stop_loss_fail_rate": 0.0,
        "avg_return": 0.021044051,
        "max_return": 0.16203699,
        "max_loss": -0.07950822,
        "avg_hold_days": 1.0,
        "sharpe_ratio": 0.0,
        "max_drawdown": 0.0
      },
      "recommendations": [
        {
          "symbol": "600758",
          "buy_price": 5.72,
          "target_price": 5.8343997,
          "stop_loss_price": 5.6628,
          "prev_close": 3.76
        },
        {
          "symbol": "600780",
          "buy_price": 7.67,
          "target_price": 7.8234,
          "stop_loss_price": 7.5933003,
          "prev_close": 5.91
        },
        {
          "symbol": "600396",
          "buy_price": 8.96,
          "target_price": 9.1392,
          "stop_loss_price": 8.8704,
          "prev_close": 3.09
        },
        {
          "symbol": "600032",
          "buy_price": 12.77,
          "target_price": 13.0254,
          "stop_loss_price": 12.642301,
          "prev_close": 7.83
        },
        {
          "symbol": "000539",
          "buy_price": 7.68,
          "target_price": 7.8335996,
          "stop_loss_price": 7.6032,
          "prev_close": 5.2
        }
      ]
    },
    {
      "strategy_name": "ATR选股策略",
      "signal_name": "地包天信号",
      "target_name": "收益率目标 2% / 1天",
      "performance": {
        "success_rate": 0.16666667,
        "stop_loss_rate": 0.0,
        "stop_loss_fail_rate": 0.0,
        "avg_return": -0.005905836,
        "max_return": 0.1004962,
        "max_loss": -0.10018666,
        "avg_hold_days": 1.0,
        "sharpe_ratio": 0.0,
        "max_drawdown": 0.0
      },
      "recommendations": []
    },
    {
      "strategy_name": "成交量萎缩策略",
      "signal_name": "开盘价信号",
      "target_name": "收益率目标 2% / 1天",
      "performance": {
        "success_rate": 0.15833335,
        "stop_loss_rate": 0.14166667,
        "stop_loss_fail_rate": 0.0,
        "avg_return": -0.005308539,
        "max_return": 0.11428569,
        "max_loss": -0.086153835,
        "avg_hold_days": 1.0,
        "sharpe_ratio": 0.0,
        "max_drawdown": 0.0
      },
      "recommendations": [
        {
          "symbol": "001225",
          "buy_price": 48.49,
          "target_price": 49.4598,
          "stop_loss_price": 48.0051,
          "prev_close": 32.82
        },
        {
          "symbol": "600331",
          "buy_price": 14.52,
          "target_price": 14.8104,
          "stop_loss_price": 14.374801,
          "prev_close": 6.99
        },
        {
          "symbol": "002637",
          "buy_price": 11.56,
          "target_price": 11.791201,
          "stop_loss_price": 11.444401,
          "prev_close": 9.46
        },
        {
          "symbol": "600370",
          "buy_price": 2.63,
          "target_price": 2.6826,
          "stop_loss_price": 2.6037002,
          "prev_close": 1.96
        },
        {
          "symbol": "002182",
          "buy_price": 15.66,
          "target_price": 15.9732,
          "stop_loss_price": 15.5034,
          "prev_close": 11.4
        }
      ]
    },
    {
      "strategy_name": "成交量萎缩策略",
      "signal_name": "地包天信号",
      "target_name": "收益率目标 2% / 1天",
      "performance": {
        "success_rate": 0.041666668,
        "stop_loss_rate": 0.22222222,
        "stop_loss_fail_rate": 0.0,
        "avg_return": -0.015351872,
        "max_return": 0.024727993,
        "max_loss": -0.08685798,
        "avg_hold_days": 1.0,
        "sharpe_ratio": 0.0,
        "max_drawdown": 0.0
      },
      "recommendations": []
    },
    {
      "strategy_name": "突破回踩策略",
      "signal_name": "开盘价信号",
      "target_name": "收益率目标 2% / 1天",
      "performance": {
        "success_rate": 0.19999999,
        "stop_loss_rate": 0.21666667,
        "stop_loss_fail_rate": 0.0,
        "avg_return": -0.003376875,
        "max_return": 0.10042741,
        "max_loss": -0.0760761,
        "avg_hold_days": 1.0,
        "sharpe_ratio": 0.0,
        "max_drawdown": 0.0
      },
      "recommendations": [
        {
          "symbol": "002358",
          "buy_price": 7.76,
          "target_price": 7.9152,
          "stop_loss_price": 7.6824,
          "prev_close": 5.22
        },
        {
          "symbol": "002366",
          "buy_price": 7.96,
          "target_price": 8.1192,
          "stop_loss_price": 7.8804,
          "prev_close": 7.42
        },
        {
          "symbol": "603985",
          "buy_price": 19.75,
          "target_price": 20.145,
          "stop_loss_price": 19.5525,
          "prev_close": 15.64
        },
        {
          "symbol": "605060",
          "buy_price": 55.72,
          "target_price": 56.8344,
          "stop_loss_price": 55.1628,
          "prev_close": 17.97
        },
        {
          "symbol": "002022",
          "buy_price": 5.74,
          "target_price": 5.8547997,
          "stop_loss_price": 5.6826,
          "prev_close": 5.98
        }
      ]
    },
    {
      "strategy_name": "突破回踩策略",
      "signal_name": "地包天信号",
      "target_name": "收益率目标 2% / 1天",
      "performance": {
        "success_rate": 0.15277778,
        "stop_loss_rate": 0.15789473,
        "stop_loss_fail_rate": 0.0,
        "avg_return": -0.00670804,
        "max_return": 0.09997636,
        "max_loss": -0.07317073,
        "avg_hold_days": 1.0,
        "sharpe_ratio": 0.0,
        "max_drawdown": 0.0
      },
      "recommendations": []
    },
    {
      "strategy_name": "ATR选股策略",
      "signal_name": "收盘价信号",
      "target_name": "收益率目标 6% / 3天",
      "performance": {
        "success_rate": 0.36666667,
        "stop_loss_rate": 0.07,
        "stop_loss_fail_rate": 0.0,
        "avg_return": 0.013372669,
        "max_return": 0.21109119,
        "max_loss": -0.14219469,
        "avg_hold_days": 1.39,
        "sharpe_ratio": 0.0,
        "max_drawdown": 0.0
      },
      "recommendations": [
        {
          "symbol": "600758",
          "buy_price": 6.14,
          "target_price": 6.5083995,
          "stop_loss_price": 6.0786,
          "prev_close": 3.76
        },
        {
          "symbol": "600780",
          "buy_price": 8.43,
          "target_price": 8.9358,
          "stop_loss_price": 8.3457,
          "prev_close": 5.91
        },
        {
          "symbol": "600396",
          "buy_price": 8.88,
          "target_price": 9.4128,
          "stop_loss_price": 8.791201,
          "prev_close": 3.09
        },
        {
          "symbol": "600032",
          "buy_price": 12.61,
          "target_price": 13.366599,
          "stop_loss_price": 12.4839,
          "prev_close": 7.83
        },
        {
          "symbol": "000539",
          "buy_price": 7.49,
          "target_price": 7.9393992,
          "stop_loss_price": 7.4150996,
          "prev_close": 5.2
        }
      ]
    },
    {
      "strategy_name": "ATR选股策略",
      "signal_name": "开盘价信号",
      "target_name": "收益率目标 6% / 3天",
      "performance": {
        "success_rate": 0.475,
        "stop_loss_rate": 0.07,
        "stop_loss_fail_rate": 0.0,
        "avg_return": 0.040962607,
        "max_return": 0.30496454,
        "max_loss": -0.1824104,
        "avg_hold_days": 1.39,
        "sharpe_ratio": 0.0,
        "max_drawdown": 0.0
      },
      "recommendations": [
        {
          "symbol": "600758",
          "buy_price": 5.72,
          "target_price": 6.0631995,
          "stop_loss_price": 5.6628,
          "prev_close": 3.76
        },
        {
          "symbol": "600780",
          "buy_price": 7.67,
          "target_price": 8.130199,
          "stop_loss_price": 7.5933003,
          "prev_close": 5.91
        },
        {
          "symbol": "600396",
          "buy_price": 8.96,
          "target_price": 9.4976,
          "stop_loss_price": 8.8704,
          "prev_close": 3.09
        },
        {
          "symbol": "600032",
          "buy_price": 12.77,
          "target_price": 13.5362,
          "stop_loss_price": 12.642301,
          "prev_close": 7.83
        },
        {
          "symbol": "000539",
          "buy_price": 7.68,
          "target_price": 8.1407995,
          "stop_loss_price": 7.6032,
          "prev_close": 5.2
        }
      ]
    },
    {
      "strategy_name": "ATR选股策略",
      "signal_name": "地包天信号",
      "target_name": "收益率目标 6% / 3天",
      "performance": {
        "success_rate": 0.083333336,
        "stop_loss_rate": 0.0,
        "stop_loss_fail_rate": 0.0,
        "avg_return": -0.01947232,
        "max_return": 0.20532006,
        "max_loss": -0.19103919,
        "avg_hold_days": 1.6666666,
        "sharpe_ratio": 0.0,
        "max_drawdown": 0.0
      },
      "recommendations": []
    },
    {
      "strategy_name": "成交量萎缩策略",
      "signal_name": "收盘价信号",
      "target_name": "收益率目标 6% / 3天",
      "performance": {
        "success_rate": 0.083333336,
        "stop_loss_rate": 0.11,
        "stop_loss_fail_rate": 0.0,
        "avg_return": -0.014969129,
        "max_return": 0.20967741,
        "max_loss": -0.12676053,
        "avg_hold_days": 1.69,
        "sharpe_ratio": 0.0,
        "max_drawdown": 0.0
      },
      "recommendations": [
        {
          "symbol": "001225",
          "buy_price": 47.0,
          "target_price": 49.819996,
          "stop_loss_price": 46.53,
          "prev_close": 32.82
        },
        {
          "symbol": "600331",
          "buy_price": 14.1,
          "target_price": 14.945999,
          "stop_loss_price": 13.959001,
          "prev_close": 6.99
        },
        {
          "symbol": "002637",
          "buy_price": 11.13,
          "target_price": 11.797799,
          "stop_loss_price": 11.018701,
          "prev_close": 9.46
        },
        {
          "symbol": "600370",
          "buy_price": 2.51,
          "target_price": 2.6606,
          "stop_loss_price": 2.4849,
          "prev_close": 1.96
        },
        {
          "symbol": "002182",
          "buy_price": 15.21,
          "target_price": 16.122599,
          "stop_loss_price": 15.0579,
          "prev_close": 11.4
        }
      ]
    },
    {
      "strategy_name": "成交量萎缩策略",
      "signal_name": "开盘价信号",
      "target_name": "收益率目标 6% / 3天",
      "performance": {
        "success_rate": 0.10000002,
        "stop_loss_rate": 0.12,
        "stop_loss_fail_rate": 0.0,
        "avg_return": -0.017415302,
        "max_return": 0.22857147,
        "max_loss": -0.12676053,
        "avg_hold_days": 1.63,
        "sharpe_ratio": 0.0,
        "max_drawdown": 0.0
      },
      "recommendations": [
        {
          "symbol": "001225",
          "buy_price": 48.49,
          "target_price": 51.3994,
          "stop_loss_price": 48.0051,
          "prev_close": 32.82
        },
        {
          "symbol": "600331",
          "buy_price": 14.52,
          "target_price": 15.3912,
          "stop_loss_price": 14.374801,
          "prev_close": 6.99
        },
        {
          "symbol": "002637",
          "buy_price": 11.56,
          "target_price": 12.2536,
          "stop_loss_price": 11.444401,
          "prev_close": 9.46
        },
        {
          "symbol": "600370",
          "buy_price": 2.63,
          "target_price": 2.7878,
          "stop_loss_price": 2.6037002,
          "prev_close": 1.96
        },
        {
          "symbol": "002182",
          "buy_price": 15.66,
          "target_price": 16.5996,
          "stop_loss_price": 15.5034,
          "prev_close": 11.4
        }
      ]
    },
    {
      "strategy_name": "成交量萎缩策略",
      "signal_name": "地包天信号",
      "target_name": "收益率目标 6% / 3天",
      "performance": {
        "success_rate": 0.055555556,
        "stop_loss_rate": 0.1764706,
        "stop_loss_fail_rate": 0.0,
        "avg_return": -0.02295469,
        "max_return": 0.13818657,
        "max_loss": -0.09365557,
        "avg_hold_days": 1.4117647,
        "sharpe_ratio": 0.0,
        "max_drawdown": 0.0
      },
      "recommendations": []
    },
    {
      "strategy_name": "突破回踩策略",
      "signal_name": "收盘价信号",
      "target_name": "收益率目标 6% / 3天",
      "performance": {
        "success_rate": 0.10833333,
        "stop_loss_rate": 0.17,
        "stop_loss_fail_rate": 0.0,
        "avg_return": -0.02010755,
        "max_return": 0.15453047,
        "max_loss": -0.14967561,
        "avg_hold_days": 1.41,
        "sharpe_ratio": 0.0,
        "max_drawdown": 0.0
      },
      "recommendations": [
        {
          "symbol": "002358",
          "buy_price": 7.51,
          "target_price": 7.9606,
          "stop_loss_price": 7.4349003,
          "prev_close": 5.22
        },
        {
          "symbol": "002366",
          "buy_price": 7.66,
          "target_price": 8.119599,
          "stop_loss_price": 7.5834,
          "prev_close": 7.42
        },
        {
          "symbol": "603985",
          "buy_price": 19.5,
          "target_price": 20.669998,
          "stop_loss_price": 19.305,
          "prev_close": 15.64
        },
        {
          "symbol": "605060",
          "buy_price": 53.8,
          "target_price": 57.027996,
          "stop_loss_price": 53.262,
          "prev_close": 17.97
        },
        {
          "symbol": "002022",
          "buy_price": 5.72,
          "target_price": 6.0631995,
          "stop_loss_price": 5.6628,
          "prev_close": 5.98
        }
      ]
    },
    {
      "strategy_name": "突破回踩策略",
      "signal_name": "开盘价信号",
      "target_name": "收益率目标 6% / 3天",
      "performance": {
        "success_rate": 0.125,
        "stop_loss_rate": 0.13,
        "stop_loss_fail_rate": 0.0,
        "avg_return": -0.023633676,
        "max_return": 0.13499999,
        "max_loss": -0.14312337,
        "avg_hold_days": 1.36,
        "sharpe_ratio": 0.0,
        "max_drawdown": 0.0
      },
      "recommendations": [
        {
          "symbol": "002358",
          "buy_price": 7.76,
          "target_price": 8.2256,
          "stop_loss_price": 7.6824,
          "prev_close": 5.22
        },
        {
          "symbol": "002366",
          "buy_price": 7.96,
          "target_price": 8.437599,
          "stop_loss_price": 7.8804,
          "prev_close": 7.42
        },
        {
          "symbol": "603985",
          "buy_price": 19.75,
          "target_price": 20.935,
          "stop_loss_price": 19.5525,
          "prev_close": 15.64
        },
        {
          "symbol": "605060",
          "buy_price": 55.72,
          "target_price": 59.063198,
          "stop_loss_price": 55.1628,
          "prev_close": 17.97
        },
        {
          "symbol": "002022",
          "buy_price": 5.74,
          "target_price": 6.084399,
          "stop_loss_price": 5.6826,
          "prev_close": 5.98
        }
      ]
    },
    {
      "strategy_name": "突破回踩策略",
      "signal_name": "地包天信号",
      "target_name": "收益率目标 6% / 3天",
      "performance": {
        "success_rate": 0.1875,
        "stop_loss_rate": 0.15789473,
        "stop_loss_fail_rate": 0.0,
        "avg_return": -0.008792934,
        "max_return": 0.1357947,
        "max_loss": -0.14730483,
        "avg_hold_days": 1.2105263,
        "sharpe_ratio": 0.0,
        "max_drawdown": 0.0
      },
      "recommendations": []
    },
    {
      "strategy_name": "ATR选股策略",
      "signal_name": "收盘价信号",
      "target_name": "收益率目标 1% / 5天",
      "performance": {
        "success_rate": 0.4416667,
        "stop_loss_rate": 0.1,
        "stop_loss_fail_rate": 0.0,
        "avg_return": 0.01576157,
        "max_return": 0.31263852,
        "max_loss": -0.25423726,
        "avg_hold_days": 1.1625,
        "sharpe_ratio": 0.0,
        "max_drawdown": 0.0
      },
      "recommendations": [
        {
          "symbol": "600758",
          "buy_price": 6.14,
          "target_price": 6.2014,
          "stop_loss_price": 6.0786,
          "prev_close": 3.76
        },
        {
          "symbol": "600780",
          "buy_price": 8.43,
          "target_price": 8.5143,
          "stop_loss_price": 8.3457,
          "prev_close": 5.91
        },
        {
          "symbol": "600396",
          "buy_price": 8.88,
          "target_price": 8.9688,
          "stop_loss_price": 8.791201,
          "prev_close": 3.09
        },
        {
          "symbol": "600032",
          "buy_price": 12.61,
          "target_price": 12.736099,
          "stop_loss_price": 12.4839,
          "prev_close": 7.83
        },
        {
          "symbol": "000539",
          "buy_price": 7.49,
          "target_price": 7.5649,
          "stop_loss_price": 7.4150996,
          "prev_close": 5.2
        }
      ]
    },
    {
      "strategy_name": "ATR选股策略",
      "signal_name": "开盘价信号",
      "target_name": "收益率目标 1% / 5天",
      "performance": {
        "success_rate": 0.5083334,
        "stop_loss_rate": 0.0,
        "stop_loss_fail_rate": 0.0,
        "avg_return": 0.03404642,
        "max_return": 0.42361107,
        "max_loss": -0.24347824,
        "avg_hold_days": 1.2,
        "sharpe_ratio": 0.0,
        "max_drawdown": 0.0
      },
      "recommendations": [
        {
          "symbol": "600758",
          "buy_price": 5.72,
          "target_price": 5.7771997,
          "stop_loss_price": 5.6628,
          "prev_close": 3.76
        },
        {
          "symbol": "600780",
          "buy_price": 7.67,
          "target_price": 7.7467,
          "stop_loss_price": 7.5933003,
          "prev_close": 5.91
        },
        {
          "symbol": "600396",
          "buy_price": 8.96,
          "target_price": 9.0496,
          "stop_loss_price": 8.8704,
          "prev_close": 3.09
        },
        {
          "symbol": "600032",
          "buy_price": 12.77,
          "target_price": 12.8977,
          "stop_loss_price": 12.642301,
          "prev_close": 7.83
        },
        {
          "symbol": "000539",
          "buy_price": 7.68,
          "target_price": 7.7567997,
          "stop_loss_price": 7.6032,
          "prev_close": 5.2
        }
      ]
    },
    {
      "strategy_name": "ATR选股策略",
      "signal_name": "地包天信号",
      "target_name": "收益率目标 1% / 5天",
      "performance": {
        "success_rate": 0.041666668,
        "stop_loss_rate": 0.0,
        "stop_loss_fail_rate": 0.0,
        "avg_return": -0.08298177,
        "max_return": 0.14837904,
        "max_loss": -0.21157435,
        "avg_hold_days": 1.0,
        "sharpe_ratio": 0.0,
        "max_drawdown": 0.0
      },
      "recommendations": []
    },
    {
      "strategy_name": "成交量萎缩策略",
      "signal_name": "收盘价信号",
      "target_name": "收益率目标 1% / 5天",
      "performance": {
        "success_rate": 0.29166666,
        "stop_loss_rate": 0.0875,
        "stop_loss_fail_rate": 0.0,
        "avg_return": -0.015220349,
        "max_return": 0.4637097,
        "max_loss": -0.14084503,
        "avg_hold_days": 1.25,
        "sharpe_ratio": 0.0,
        "max_drawdown": 0.0
      },
      "recommendations": [
        {
          "symbol": "001225",
          "buy_price": 47.0,
          "target_price": 47.47,
          "stop_loss_price": 46.53,
          "prev_close": 32.82
        },
        {
          "symbol": "600331",
          "buy_price": 14.1,
          "target_price": 14.241,
          "stop_loss_price": 13.959001,
          "prev_close": 6.99
        },
        {
          "symbol": "002637",
          "buy_price": 11.13,
          "target_price": 11.2413,
          "stop_loss_price": 11.018701,
          "prev_close": 9.46
        },
        {
          "symbol": "600370",
          "buy_price": 2.51,
          "target_price": 2.5351,
          "stop_loss_price": 2.4849,
          "prev_close": 1.96
        },
        {
          "symbol": "002182",
          "buy_price": 15.21,
          "target_price": 15.3621,
          "stop_loss_price": 15.0579,
          "prev_close": 11.4
        }
      ]
    },
    {
      "strategy_name": "成交量萎缩策略",
      "signal_name": "开盘价信号",
      "target_name": "收益率目标 1% / 5天",
      "performance": {
        "success_rate": 0.3,
        "stop_loss_rate": 0.0375,
        "stop_loss_fail_rate": 0.0,
        "avg_return": -0.0237543,
        "max_return": 0.4637097,
        "max_loss": -0.14266305,
        "avg_hold_days": 1.2125,
        "sharpe_ratio": 0.0,
        "max_drawdown": 0.0
      },
      "recommendations": [
        {
          "symbol": "001225",
          "buy_price": 48.49,
          "target_price": 48.974903,
          "stop_loss_price": 48.0051,
          "prev_close": 32.82
        },
        {
          "symbol": "600331",
          "buy_price": 14.52,
          "target_price": 14.6652,
          "stop_loss_price": 14.374801,
          "prev_close": 6.99
        },
        {
          "symbol": "002637",
          "buy_price": 11.56,
          "target_price": 11.6756,
          "stop_loss_price": 11.444401,
          "prev_close": 9.46
        },
        {
          "symbol": "600370",
          "buy_price": 2.63,
          "target_price": 2.6563,
          "stop_loss_price": 2.6037002,
          "prev_close": 1.96
        },
        {
          "symbol": "002182",
          "buy_price": 15.66,
          "target_price": 15.8166,
          "stop_loss_price": 15.5034,
          "prev_close": 11.4
        }
      ]
    },
    {
      "strategy_name": "成交量萎缩策略",
      "signal_name": "地包天信号",
      "target_name": "收益率目标 1% / 5天",
      "performance": {
        "success_rate": 0.15277778,
        "stop_loss_rate": 0.2857143,
        "stop_loss_fail_rate": 0.0,
        "avg_return": -0.0369438,
        "max_return": 0.16346991,
        "max_loss": -0.13319597,
        "avg_hold_days": 1.0714285,
        "sharpe_ratio": 0.0,
        "max_drawdown": 0.0
      },
      "recommendations": []
    },
    {
      "strategy_name": "突破回踩策略",
      "signal_name": "收盘价信号",
      "target_name": "收益率目标 1% / 5天",
      "performance": {
        "success_rate": 0.26666668,
        "stop_loss_rate": 0.1,
        "stop_loss_fail_rate": 0.0,
        "avg_return": -0.049554855,
        "max_return": 0.09595116,
        "max_loss": -0.16823341,
        "avg_hold_days": 1.0625,
        "sharpe_ratio": 0.0,
        "max_drawdown": 0.0
      },
      "recommendations": [
        {
          "symbol": "002358",
          "buy_price": 7.51,
          "target_price": 7.5851,
          "stop_loss_price": 7.4349003,
          "prev_close": 5.22
        },
        {
          "symbol": "002366",
          "buy_price": 7.66,
          "target_price": 7.7366,
          "stop_loss_price": 7.5834,
          "prev_close": 7.42
        },
        {
          "symbol": "603985",
          "buy_price": 19.5,
          "target_price": 19.695,
          "stop_loss_price": 19.305,
          "prev_close": 15.64
        },
        {
          "symbol": "605060",
          "buy_price": 53.8,
          "target_price": 54.337997,
          "stop_loss_price": 53.262,
          "prev_close": 17.97
        },
        {
          "symbol": "002022",
          "buy_price": 5.72,
          "target_price": 5.7771997,
          "stop_loss_price": 5.6628,
          "prev_close": 5.98
        }
      ]
    },
    {
      "strategy_name": "突破回踩策略",
      "signal_name": "开盘价信号",
      "target_name": "收益率目标 1% / 5天",
      "performance": {
        "success_rate": 0.26666668,
        "stop_loss_rate": 0.0625,
        "stop_loss_fail_rate": 0.0,
        "avg_return": -0.058595855,
        "max_return": 0.073913075,
        "max_loss": -0.20720719,
        "avg_hold_days": 1.0375,
        "sharpe_ratio": 0.0,
        "max_drawdown": 0.0
      },
      "recommendations": [
        {
          "symbol": "002358",
          "buy_price": 7.76,
          "target_price": 7.8376,
          "stop_loss_price": 7.6824,
          "prev_close": 5.22
        },
        {
          "symbol": "002366",
          "buy_price": 7.96,
          "target_price": 8.0396,
          "stop_loss_price": 7.8804,
          "prev_close": 7.42
        },
        {
          "symbol": "603985",
          "buy_price": 19.75,
          "target_price": 19.9475,
          "stop_loss_price": 19.5525,
          "prev_close": 15.64
        },
        {
          "symbol": "605060",
          "buy_price": 55.72,
          "target_price": 56.277203,
          "stop_loss_price": 55.1628,
          "prev_close": 17.97
        },
        {
          "symbol": "002022",
          "buy_price": 5.74,
          "target_price": 5.7973995,
          "stop_loss_price": 5.6826,
          "prev_close": 5.98
        }
      ]
    },
    {
      "strategy_name": "突破回踩策略",
      "signal_name": "地包天信号",
      "target_name": "收益率目标 1% / 5天",
      "performance": {
        "success_rate": 0.32500002,
        "stop_loss_rate": 0.0,
        "stop_loss_fail_rate": 0.0,
        "avg_return": -0.021315252,
        "max_return": 0.09286467,
        "max_loss": -0.16496287,
        "avg_hold_days": 1.2,
        "sharpe_ratio": 0.0,
        "max_drawdown": 0.0
      },
      "recommendations": []
    }
  ]
}